{
  "name": ".dracula",
  "type": "dark",
  "semanticHighlighting": true,
  "semanticTokenColors": {
    "function": "#50fa7b",
    "class": "#50fa7b",
    "type": "#8be9fd",
    "method": "#50fa7b",
    "parameter": "#ffb86c",
    "property": "#bd93f9",
    "variable.defaultLibrary": "#8be9fd"
  },
  "colors": {
    "terminalCursor.background": "#000000",
    "terminal.ansiBlack": "#6272a4",
    "terminal.ansiBrightBlack": "#6272a4",
    "terminal.ansiRed": "#ff79c6",
    "terminal.ansiBrightRed": "#ff79c6",
    "terminal.ansiYellow": "#f1fa8c",
    "terminal.ansiBrightYellow": "#f1fa8c",
    "terminal.ansiGreen": "#50fa7b",
    "terminal.ansiBrightGreen": "#50fa7b",
    "terminal.ansiBlue": "#bd93f9",
    "terminal.ansiBrightBlue": "#bd93f9",
    "terminal.ansiMagenta": "#ffb86c",
    "terminal.ansiBrightMagenta": "#ffb86c",
    "terminal.ansiCyan": "#8be9fd",
    "terminal.ansiBrightCyan": "#8be9fd",
    "terminal.ansiWhite": "#f8f8f2",
    "terminal.ansiBrightWhite": "#f8f8f2",
    "terminal.selectionBackground": "#ff79c620",

    "activityBar.background": "#2f313f",
    "titleBar.activeBackground": "#2f313f",
    "titleBar.inactiveBackground": "#2f313f",
    "statusBar.background": "#2f313f",
    "statusBar.noFolderBackground": "#2f313f",
    "sideBar.background": "#242630",
    "editorSuggestWidget.background": "#242630",
    "peekViewResult.background": "#242630",
    "checkbox.background": "#242630",
    "dropdown.background": "#242630",
    "input.background": "#242630",
    "widget.shadow": "#1e1f26",
    "textSeparator.foreground": "#242630",
    "button.foreground": "#242630",
    "inputValidation.errorForeground": "#242630",
    "inputValidation.infoForeground": "#242630",
    "inputValidation.warningForeground": "#242630",
    "scrollbar.shadow": "#1e1f2600",
    "badge.foreground": "#242630",
    "panel.background": "#242630",

    "tab.activeBackground": "#282a36",
    "tab.inactiveBackground": "#242630",
    "editorGroupHeader.tabsBackground": "#242630",
    "editorGroupHeader.noTabsBackground": "#242630",
    "tab.hoverBackground": "#2f313fA0",
    "tab.border": "#1e1f26A0",
    "editorGroupHeader.border": "#1e1f26A0",
    "sideBar.border": "#1e1f26A0",
    "titleBar.border": "#1e1f26D0",
    "statusBar.border": "#1e1f26A0",
    "activityBar.border": "#1e1f26A0",
    "editorGroup.border": "#1e1f26",
    "interactiveEditor.shadow": "#1e1f26",

    "editorPane.background": "#282a36",
    "activityBarBadge.foreground": "#282a36",
    "editor.background": "#282a36",
    "editorWidget.background": "#282a36",
    "editorMarkerNavigation.background": "#282a36",
    "menu.background": "#282a36",
    "notifications.background": "#282a36",

    "editorLineNumber.foreground": "#6272a4",
    "panel.border": "#6272a400",
    "editorIndentGuide.background": "#6272a430",
    "editorOverviewRuler.border": "#6272a410",
    "editorWidget.resizeBorder": "#6272a430",
    "editorSuggestWidget.border": "#6272a430",
    "editorHoverWidget.border": "#6272a430",
    "dropdown.border": "#6272a430",
    "input.border": "#6272a430",
    "scrollbarSlider.background": "#6272a450",
    "scrollbarSlider.hoverBackground": "#6272a4A0",
    "scrollbarSlider.activeBackground": "#6272a4",
    "sideBarSectionHeader.background": "#6272a420",
    "statusBarItem.hoverBackground": "#6272a430",
    "editor.selectionBackground": "#6272a480",
    "menu.separatorBackground": "#6272a4",
    "editor.wordHighlightBackground": "#6272a480",
    "editor.selectionHighlightBackground": "#6272a480",
    "editor.wordHighlightBorder": "#6272a4",
    "editorBracketMatch.background": "#6272a430",
    "editorBracketMatch.border": "#6272a4",
    "activityBar.inactiveForeground": "#f8f8f250",

    "statusBar.foreground": "#c2c2c2",
    "sideBar.foreground": "#f8f8f2A0",

    "inputValidation.warningBackground": "#50fa7b90",
    "inputValidation.warningBorder": "#50fa7b",
    "statusBar.debuggingBackground": "#50fa7b10",

    "errorForeground": "#ff79c6",
    "inputValidation.errorBackground": "#ff79c690",
    "inputValidation.errorBorder": "#ff79c6",

    "textLink.activeForeground": "#ffb86c",
    "inputValidation.infoBackground": "#ffb86c90",
    "inputValidation.infoBorder": "#ffb86c",

    "editor.lineHighlightBackground": "#6272a418",
    "editor.lineHighlightBorder": "#00000000",
    "editorLineNumber.activeForeground": "#ff79c6",
    "focusBorder": "#ff79c6",
    "editor.findMatchBackground": "#ff79c630",
    "editor.findMatchHighlightBackground": "#ff79c610",
    "editor.findMatchHighlightBorder": "#ff79c630",
    "selection.background": "#ff79c680",
    "list.hoverBackground": "#ff79c610",
    "textLink.foreground": "#ff79c6",
    "progressBar.background": "#ff79c6",
    "list.activeSelectionBackground": "#ff79c620",
    "list.focusBackground": "#ff79c630",
    "list.inactiveSelectionBackground": "#2f313fA0",
    "activityBar.dropBorder": "#f8f8f2",
    "activityBarBadge.background": "#ff79c6",
    "activityBar.activeBorder": "#ff79c6",
    "activityBar.activeFocusBorder": "#f8f8f2",
    "minimap.selectionHighlight": "#ff79c680",
    "editorGroup.dropBackground": "#ff79c630",
    "tab.lastPinnedBorder": "#ff79c650",
    "editorCursor.foreground": "#ff79c6",
    "editor.findMatchBorder": "#ff79c6",
    "editorLink.activeForeground": "#ff79c6",
    "editorIndentGuide.activeBackground": "#ff79c660",
    "editorOverviewRuler.selectionHighlightForeground": "#ff79c6",
    "editorOverviewRuler.bracketMatchForeground": "#ff79c6",
    "panel.dropBorder": "#ff79c6",
    "panelTitle.activeBorder": "#ff79c6",
    "statusBarItem.prominentBackground": "#ff79c6",
    "menu.selectionBackground": "#ff79c6DD",
    "pickerGroup.foreground": "#ff79c6",
    "terminalCursor.foreground": "#ff79c6",
    "button.background": "#ff79c6",
    "button.hoverBackground": "#ff79c6",
    "extensionButton.prominentBackground": "#ff79c6",
    "extensionButton.prominentHoverBackground": "#ff79c6",
    "badge.background": "#ff79c6",
    "activityBar.foreground": "#f8f8f2",
    "tab.activeBorder": "#282a36",
    "tab.activeBorderTop": "#ff79c600",

    "textPreformat.foreground": "#f1fa8c",
    "editor.wordHighlightStrongBackground": "#f1fa8c50",
    "editor.wordHighlightStrongBorder": "#f1fa8c80",

    "foreground": "#f8f8f2",
    "editorWhitespace.foreground": "#f8f8f230",

    "list.errorForeground": "#ff79c6",
    "minimap.errorHighlight": "#ff79c6",
    "minimapGutter.deletedBackground": "#ff79c6",
    "editorOverviewRuler.errorForeground": "#ff79c6",
    "editorError.foreground": "#ff79c6",
    "problemsErrorIcon.foreground": "#ff79c6",
    "list.warningForeground": "#50fa7b",
    "editorOverviewRuler.warningForeground": "#50fa7b",
    "minimap.warningHighlight": "#50fa7b",
    "editorWarning.foreground": "#50fa7b",
    "problemsWarningIcon.foreground": "#50fa7b",
    "activityBar.activeBackground": "#00000000",
    "minimapGutter.addedBackground": "#f1fa8c",
    "list.highlightForeground": "#ffb86c",
    "minimapGutter.modifiedBackground": "#ffb86c",
    "tab.activeModifiedBorder": "#ffb86c",
    "editorOverviewRuler.modifiedForeground": "#ffb86c",
    "editorOverviewRuler.addedForeground": "#ffb86c",
    "editorOverviewRuler.deletedForeground": "#ffb86c",
    "editorOverviewRuler.infoForeground": "#ffb86c",
    "editor.foreground": "#f8f8f2",
    "statusBar.debuggingForeground": "#f8f8f2",
    "editorCursor.background": "#000000",
    "editor.foldBackground": "#ffb86c30",
    "editorInfo.foreground": "#ffb86c",
    "problemsInfoIcon.foreground": "#ffb86c",
    "editorGutter.modifiedBackground": "#ffb86c",
    "editorGutter.addedBackground": "#f1fa8c",
    "editorGutter.deletedBackground": "#ff79c6",
    "diffEditor.insertedTextBackground": "#f1fa8c30",
    "diffEditor.removedTextBackground": "#ff79c635",
    "editorSuggestWidget.highlightForeground": "#ffb86c",
    "editorMarkerNavigationError.background": "#ff79c6",
    "editorMarkerNavigationWarning.background": "#50fa7b",
    "editorMarkerNavigationInfo.background": "#ffb86c",
    "peekViewTitle.background": "#131321",
    "statusBarItem.prominentForeground": "#000000",
    "statusBarItem.prominentHoverBackground": "#ff79c6",
    "menu.foreground": "#f8f8f2",
    "menu.selectionForeground": "#000000",
    "notificationsErrorIcon.foreground": "#ff79c6",
    "notificationsWarningIcon.foreground": "#50fa7b",
    "notificationsInfoIcon.foreground": "#ffb86c",
    "extensionButton.prominentForeground": "#000000",
    "pickerGroup.border": "#1e1f26",
    "gitDecoration.addedResourceForeground": "#f1fa8c",
    "gitDecoration.modifiedResourceForeground": "#ffb86c",
    "gitDecoration.deletedResourceForeground": "#ff79c6",
    "gitDecoration.stageDeletedResourceForeground": "#ff79c6",
    "gitDecoration.stageModifiedResourceForeground": "#ffb86c",
    "gitDecoration.ignoredResourceForeground": "#c2c2c280",
    "settings.modifiedItemIndicator": "#ffb86c",
    "editorBracketHighlight.foreground1": "#f8f8f2",
    "editorBracketHighlight.foreground2": "#f1fa8c",
    "editorBracketHighlight.foreground3": "#50fa7b",
    "editorBracketHighlight.foreground4": "#8be9fd",
    "editorBracketHighlight.foreground5": "#ffb86c",
    "editorBracketHighlight.foreground6": "#ff79c6"
  },
  "tokenColors": [
    {
      "scope": ["variable.language.this", "variable.parameter"],
      "settings": {
        "foreground": "#ffb86c",
        "fontStyle": "italic"
      }
    },
    {
      "scope": [],
      "settings": {
        "foreground": "#ff79c6",
        "fontStyle": "italic"
      }
    },
    {
      "scope": ["punctuation.definition.heading"],
      "settings": {
        "foreground": "#ff79c6",
        "fontStyle": "bold"
      }
    },
    {
      "scope": ["entity.name.function"],
      "settings": {
        "foreground": "#50fa7b",
        "fontStyle": ""
      }
    },
    {
      "scope": [
        "entity.other.attribute-name.pseudo-element",
        "entity.other.attribute-name.pseudo-class"
      ],
      "settings": {
        "foreground": "#50fa7b",
        "fontStyle": "italic"
      }
    },
    {
      "scope": [],
      "settings": {
        "foreground": "#50fa7b",
        "fontStyle": "bold"
      }
    },
    {
      "scope": [],
      "settings": {
        "foreground": "#50fa7b",
        "fontStyle": "underline"
      }
    },
    {
      "scope": ["support.class"],
      "settings": {
        "foreground": "#8be9fd",
        "fontStyle": ""
      }
    },
    {
      "scope": ["support.type", "entity.name.type.class"],
      "settings": {
        "foreground": "#8be9fd",
        "fontStyle": ""
      }
    },
    {
      "scope": [
        "support.constant.property-value",
        "entity.name.type",
        "storage.type",
        "storage.type.function",
        "storage"
      ],
      "settings": {
        "foreground": "#8be9fd",
        "fontStyle": "italic"
      }
    },
    {
      "scope": [
        "variable.language.super",
        "constant.character.entity",
        "punctuation.definition.entity",
        "markup.quote",
        "entity.other.attribute-name.id",
        "entity.other.attribute-name.id punctuation.definition.entity",
        "variable.parameter.url",
        "entity.name.section",
        "markup.changed",
        "meta.diff.header",
        "punctuation.definition.list",
        "source.tsx punctuation.section.embedded",
        "source.jsx punctuation.section.embedded",
        "keyword.operator",
        "storage.type.function.arrow",
        "keyword.operator.assignment",
        "punctuation.accessor.optional",
        "punctuation.definition.string.template",
        "punctuation.definition.template-expression",
        "keyword.operator.spread",
        "keyword.other.unit"
      ],
      "settings": {
        "foreground": "#ff79c6",
        "fontStyle": ""
      }
    },
    {
      "scope": [
        "keyword",
        "entity.name.tag.html",
        "entity.name.tag.css",
        "keyword.operator.new",
        "storage.modifier"
      ],
      "settings": {
        "foreground": "#ff79c6",
        "fontStyle": "italic"
      }
    },
    {
      "scope": [
        "link",
        "markup.underline.link",
        "constant.other.reference.link.markdown"
      ],
      "settings": {
        "foreground": "#ff79c6",
        "fontStyle": "underline"
      }
    },
    {
      "scope": [
        "support.function",
        "string",
        "punctuation.definition.string",
        "constant.language.import-export-all",
        "meta.tag string",
        "markup.heading.setext",
        "meta.separator.markdown",
        "meta.property-value",
        "meta.property-value constant.other",
        "punctuation.section.embedded.begin.php",
        "punctuation.section.embedded.end.php",
        "markup.inserted",
        "string.template"
      ],
      "settings": {
        "foreground": "#f1fa8c",
        "fontStyle": ""
      }
    },
    {
      "scope": [],
      "settings": {
        "foreground": "#f1fa8c",
        "fontStyle": "italic"
      }
    },
    {
      "scope": [
        "meta.embedded",
        "source.groovy.embedded",
        "meta.template.expression",
        "punctuation.definition.variable",
        "support.variable.property.dom",
        "support.variable.dom",
        "support.variable.property",
        "string.interpolated.pug variable",
        "punctuation",
        "meta.brace.round.js"
      ],
      "settings": {
        "foreground": "#f8f8f2"
      }
    },
    {
      "scope": [
        "entity.other.attribute-name.class",
        "entity.other.attribute-name punctuation.definition.entity",
        "markup.deleted",
        "punctuation.definition.markdown",
        "storage.modifier.pointer",
        "punctuation.definition.typeparameters",
        "punctuation.definition.directive",
        "entity.other.inherited-class",
        "punctuation.definition.entity.css",
        "entity.other.attribute-name.id.css",
        "entity.name.tag"
      ],
      "settings": {
        "foreground": "#f8f8f2",
        "fontStyle": "italic"
      }
    },
    {
      "scope": [
        "constant.character.escape",
        "variable.language.special.self",
        "meta.tag.metadata.doctype string",
        "meta.tag.sgml.doctype",
        "markup.inline.raw",
        "meta.link punctuation.definition.string",
        "meta.image punctuation.definition.string",
        "meta.diff.range",
        "constant.other.color",
        "entity.name.tag.wildcard",
        "constant",
        "support.type.property-name.css",
        "entity.other.attribute-name.tsx"
      ],
      "settings": {
        "foreground": "#bd93f9",
        "fontStyle": "italic"
      }
    },
    {
      "scope": ["variable.other.property"],
      "settings": {
        "foreground": "#bd93f9",
        "fontStyle": ""
      }
    },
    {
      "scope": ["constant.numeric"],
      "settings": {
        "foreground": "#bd93f9",
        "fontStyle": ""
      }
    },
    {
      "scope": ["constant.language"],
      "settings": {
        "foreground": "#bd93f9",
        "fontStyle": "italic"
      }
    },
    {
      "scope": [],
      "settings": {
        "foreground": "#f8f8f2",
        "fontStyle": "bold"
      }
    },
    {
      "scope": [
        "variable.argument",
        "meta.function.parameter variable",
        "punctuation.definition.binding-pattern.array",
        "source.rust meta.type_params.rust"
      ],
      "settings": {
        "foreground": "#c9c7c2",
        "fontStyle": ""
      }
    },
    {
      "scope": ["punctuation.definition.comment", "comment"],
      "settings": {
        "foreground": "#6272a4",
        "fontStyle": "italic"
      }
    },
    {
      "scope": ["punctuation.separator", "punctuation.accessor"],
      "settings": {
        "foreground": "#6272a4",
        "fontStyle": ""
      }
    },
    {
      "scope": [
        "punctuation.definition.entity.html",
        "constant.character.entity.named.emsp.html",
        "meta.property-list entity.name.tag.css",
        "meta.tag entity.other.attribute-name",
        "entity.other.attribute-name.html",
        "property"
      ],
      "settings": {
        "foreground": "#9eabb7",
        "fontStyle": "italic"
      }
    },
    {
      "scope": [],
      "settings": {
        "foreground": "#9eabb7",
        "fontStyle": ""
      }
    },
    {
      "scope": ["punctuation.definition.tag"],
      "settings": {
        "foreground": "#9eabb7",
        "fontStyle": "italic"
      }
    },
    {
      "scope": ["entity.name.section.markdown"],
      "settings": {
        "foreground": "#c9c7c2",
        "fontStyle": "bold"
      }
    },
    {
      "scope": "markup.bold",
      "settings": {
        "fontStyle": "bold"
      }
    },
    {
      "scope": ["markup.italic"],
      "settings": {
        "fontStyle": "italic"
      }
    }
  ]
}
