{
  "name": ".yogokai one",
  "type": "dark",
  "semanticHighlighting": true,
  "semanticTokenColors": {
    "function": "#62E884",
    "class": "#62E884",
    "type": "#97E1F1",
    "method": "#62E884",
    "parameter": "#BF9EEE",
    "property": "#F6F6F4",
    "variable.defaultLibrary": "#97E1F1"
  },
  "colors": {
    "terminalCursor.background": "#000000",
    "terminal.ansiBlack": "#7B7F8B",
    "terminal.ansiBrightBlack": "#7B7F8B",
    "terminal.ansiRed": "#F286C4",
    "terminal.ansiBrightRed": "#F286C4",
    "terminal.ansiYellow": "#E7EE98",
    "terminal.ansiBrightYellow": "#E7EE98",
    "terminal.ansiGreen": "#62E884",
    "terminal.ansiBrightGreen": "#62E884",
    "terminal.ansiBlue": "#F6F6F4",
    "terminal.ansiBrightBlue": "#F6F6F4",
    "terminal.ansiMagenta": "#BF9EEE",
    "terminal.ansiBrightMagenta": "#BF9EEE",
    "terminal.ansiCyan": "#97E1F1",
    "terminal.ansiBrightCyan": "#97E1F1",
    "terminal.ansiWhite": "#F6F6F4",
    "terminal.ansiBrightWhite": "#F6F6F4",
    "terminal.selectionBackground": "#F286C420",

    "activityBar.background": "#2F3133",
    "titleBar.activeBackground": "#2F3133",
    "titleBar.inactiveBackground": "#2F3133",
    "statusBar.background": "#2F3133",
    "statusBar.noFolderBackground": "#2F3133",
    "sideBar.background": "#282A2C",
    "editorSuggestWidget.background": "#282A2C",
    "peekViewResult.background": "#282A2C",
    "checkbox.background": "#282A2C",
    "dropdown.background": "#282A2C",
    "input.background": "#282A2C",
    "widget.shadow": "#05070a",
    "textSeparator.foreground": "#282A2C",
    "button.foreground": "#282A2C",
    "inputValidation.errorForeground": "#282A2C",
    "inputValidation.infoForeground": "#282A2C",
    "inputValidation.warningForeground": "#282A2C",
    "scrollbar.shadow": "#05070a00",
    "badge.foreground": "#282A2C",
    "panel.background": "#282A2C",

    "tab.activeBackground": "#0D121B",
    "tab.inactiveBackground": "#0D121B",
    "editorGroupHeader.tabsBackground": "#0D121B",
    "editorGroupHeader.noTabsBackground": "#0D121B",
    "tab.hoverBackground": "#2F3133A0",
    "tab.border": "#05070a00",
    "editorGroupHeader.border": "#05070a00",
    "sideBar.border": "#05070aA0",
    "titleBar.border": "#05070aD0",
    "statusBar.border": "#05070aA0",
    "activityBar.border": "#05070aA0",
    "editorGroup.border": "#05070a",
    "interactiveEditor.shadow": "#05070a",

    "editorPane.background": "#0D121B",
    "activityBarBadge.foreground": "#0D121B",
    "editor.background": "#0D121B",
    "editorWidget.background": "#0D121B",
    "editorMarkerNavigation.background": "#0D121B",
    "menu.background": "#0D121B",
    "notifications.background": "#0D121B",

    "editorLineNumber.foreground": "#F6F6F460",
    "panel.border": "#F6F6F400",
    "editorIndentGuide.background": "#F6F6F418",
    "editorOverviewRuler.border": "#F6F6F410",
    "editorWidget.resizeBorder": "#F6F6F430",
    "editorSuggestWidget.border": "#F6F6F430",
    "editorHoverWidget.border": "#F6F6F430",
    "dropdown.border": "#F6F6F430",
    "input.border": "#F6F6F430",
    "scrollbarSlider.background": "#F6F6F450",
    "scrollbarSlider.hoverBackground": "#F6F6F4A0",
    "scrollbarSlider.activeBackground": "#F6F6F4",
    "sideBarSectionHeader.background": "#F6F6F420",
    "statusBarItem.hoverBackground": "#F6F6F430",
    "editor.selectionBackground": "#F6F6F420",
    "menu.separatorBackground": "#F6F6F4",
    "editor.wordHighlightBackground": "#F6F6F410",
    "editor.selectionHighlightBackground": "#F6F6F410",
    "editor.wordHighlightBorder": "#F6F6F430",
    "editorBracketMatch.background": "#F6F6F410",
    "editorBracketMatch.border": "#F6F6F430",
    "activityBar.inactiveForeground": "#F6F6F450",

    "statusBar.foreground": "#c2c2c2",
    "sideBar.foreground": "#F6F6F4A0",

    "inputValidation.warningBackground": "#62E88490",
    "inputValidation.warningBorder": "#62E884",
    "statusBar.debuggingBackground": "#62E88410",

    "errorForeground": "#F286C4",
    "inputValidation.errorBackground": "#F286C490",
    "inputValidation.errorBorder": "#F286C4",

    "textLink.activeForeground": "#BF9EEE",
    "inputValidation.infoBackground": "#BF9EEE90",
    "inputValidation.infoBorder": "#BF9EEE",

    "editor.lineHighlightBackground": "#7B7F8B18",
    "editor.lineHighlightBorder": "#00000000",
    "editorLineNumber.activeForeground": "#97E1F1",
    "focusBorder": "#97E1F1",
    "editor.findMatchBackground": "#97E1F130",
    "editor.findMatchHighlightBackground": "#97E1F110",
    "editor.findMatchHighlightBorder": "#97E1F130",
    "selection.background": "#97E1F180",
    "list.hoverBackground": "#97E1F110",
    "textLink.foreground": "#97E1F1",
    "progressBar.background": "#97E1F1",
    "list.activeSelectionBackground": "#97E1F120",
    "list.focusBackground": "#97E1F130",
    "list.inactiveSelectionBackground": "#2F3133A0",
    "activityBar.dropBorder": "#F6F6F4",
    "activityBarBadge.background": "#97E1F1",
    "activityBar.activeBorder": "#97E1F1",
    "activityBar.activeFocusBorder": "#F6F6F4",
    "minimap.selectionHighlight": "#97E1F180",
    "editorGroup.dropBackground": "#97E1F130",
    "tab.lastPinnedBorder": "#97E1F150",
    "editorCursor.foreground": "#97E1F1",
    "editor.findMatchBorder": "#97E1F1",
    "editorLink.activeForeground": "#97E1F1",
    "editorIndentGuide.activeBackground": "#97E1F160",
    "editorOverviewRuler.selectionHighlightForeground": "#97E1F1",
    "editorOverviewRuler.bracketMatchForeground": "#97E1F1",
    "panel.dropBorder": "#97E1F1",
    "panelTitle.activeBorder": "#97E1F1",
    "statusBarItem.prominentBackground": "#97E1F1",
    "menu.selectionBackground": "#97E1F1DD",
    "pickerGroup.foreground": "#97E1F1",
    "terminalCursor.foreground": "#97E1F1",
    "button.background": "#97E1F1",
    "button.hoverBackground": "#97E1F1",
    "extensionButton.prominentBackground": "#97E1F1",
    "extensionButton.prominentHoverBackground": "#97E1F1",
    "badge.background": "#97E1F1",
    "activityBar.foreground": "#F6F6F4",
    "tab.activeBorder": "#97E1F1",
    "tab.activeBorderTop": "#97E1F100",

    "textPreformat.foreground": "#E7EE98",
    "editor.wordHighlightStrongBackground": "#E7EE9850",
    "editor.wordHighlightStrongBorder": "#E7EE9880",

    "foreground": "#F6F6F4",
    "editorWhitespace.foreground": "#F6F6F430",

    "list.errorForeground": "#F286C4",
    "minimap.errorHighlight": "#F286C4",
    "minimapGutter.deletedBackground": "#F286C4",
    "editorOverviewRuler.errorForeground": "#F286C4",
    "editorError.foreground": "#F286C4",
    "problemsErrorIcon.foreground": "#F286C4",
    "list.warningForeground": "#62E884",
    "editorOverviewRuler.warningForeground": "#62E884",
    "minimap.warningHighlight": "#62E884",
    "editorWarning.foreground": "#62E884",
    "problemsWarningIcon.foreground": "#62E884",
    "activityBar.activeBackground": "#00000000",
    "minimapGutter.addedBackground": "#E7EE98",
    "list.highlightForeground": "#BF9EEE",
    "minimapGutter.modifiedBackground": "#BF9EEE",
    "tab.activeModifiedBorder": "#BF9EEE",
    "editorOverviewRuler.modifiedForeground": "#BF9EEE",
    "editorOverviewRuler.addedForeground": "#BF9EEE",
    "editorOverviewRuler.deletedForeground": "#BF9EEE",
    "editorOverviewRuler.infoForeground": "#BF9EEE",
    "editor.foreground": "#F6F6F4",
    "statusBar.debuggingForeground": "#F6F6F4",
    "editorCursor.background": "#000000",
    "editor.foldBackground": "#BF9EEE30",
    "editorInfo.foreground": "#BF9EEE",
    "problemsInfoIcon.foreground": "#BF9EEE",
    "editorGutter.modifiedBackground": "#BF9EEE",
    "editorGutter.addedBackground": "#E7EE98",
    "editorGutter.deletedBackground": "#F286C4",
    "diffEditor.insertedTextBackground": "#E7EE9830",
    "diffEditor.removedTextBackground": "#F286C435",
    "editorSuggestWidget.highlightForeground": "#BF9EEE",
    "editorMarkerNavigationError.background": "#F286C4",
    "editorMarkerNavigationWarning.background": "#62E884",
    "editorMarkerNavigationInfo.background": "#BF9EEE",
    "peekViewTitle.background": "#131321",
    "statusBarItem.prominentForeground": "#000000",
    "statusBarItem.prominentHoverBackground": "#97E1F1",
    "menu.foreground": "#F6F6F4",
    "menu.selectionForeground": "#000000",
    "notificationsErrorIcon.foreground": "#F286C4",
    "notificationsWarningIcon.foreground": "#62E884",
    "notificationsInfoIcon.foreground": "#BF9EEE",
    "extensionButton.prominentForeground": "#000000",
    "pickerGroup.border": "#05070a",
    "gitDecoration.addedResourceForeground": "#E7EE98",
    "gitDecoration.modifiedResourceForeground": "#BF9EEE",
    "gitDecoration.deletedResourceForeground": "#F286C4",
    "gitDecoration.stageDeletedResourceForeground": "#F286C4",
    "gitDecoration.stageModifiedResourceForeground": "#BF9EEE",
    "gitDecoration.ignoredResourceForeground": "#c2c2c280",
    "settings.modifiedItemIndicator": "#BF9EEE",
    "editorBracketHighlight.foreground1": "#F6F6F4",
    "editorBracketHighlight.foreground2": "#E7EE98",
    "editorBracketHighlight.foreground3": "#62E884",
    "editorBracketHighlight.foreground4": "#97E1F1",
    "editorBracketHighlight.foreground5": "#BF9EEE",
    "editorBracketHighlight.foreground6": "#F286C4"
  },
  "tokenColors": [
    {
      "scope": ["variable.language.this", "variable.parameter"],
      "settings": {
        "foreground": "#BF9EEE",
        "fontStyle": ""
      }
    },
    {
      "scope": [],
      "settings": {
        "foreground": "#F286C4",
        "fontStyle": "italic"
      }
    },
    {
      "scope": ["punctuation.definition.heading"],
      "settings": {
        "foreground": "#F286C4",
        "fontStyle": "bold"
      }
    },
    {
      "scope": [
        "entity.name.function",
        "entity.other.attribute-name.pseudo-element",
        "entity.other.attribute-name.pseudo-class",
        "entity.other.attribute-name.html"
      ],
      "settings": {
        "foreground": "#62E884",
        "fontStyle": ""
      }
    },
    {
      "scope": [],
      "settings": {
        "foreground": "#62E884",
        "fontStyle": "italic"
      }
    },
    {
      "scope": [],
      "settings": {
        "foreground": "#62E884",
        "fontStyle": "bold"
      }
    },
    {
      "scope": [],
      "settings": {
        "foreground": "#62E884",
        "fontStyle": "underline"
      }
    },
    {
      "scope": ["support.class"],
      "settings": {
        "foreground": "#97E1F1",
        "fontStyle": ""
      }
    },
    {
      "scope": [
        "support.type",
        "entity.name.type.class",
        "support.constant.property-value",
        "entity.name.type"
      ],
      "settings": {
        "foreground": "#97E1F1",
        "fontStyle": ""
      }
    },
    {
      "scope": [],
      "settings": {
        "foreground": "#97E1F1",
        "fontStyle": "italic"
      }
    },
    {
      "scope": [
        "variable.language.super",
        "constant.character.entity",
        "punctuation.definition.entity",
        "markup.quote",
        "entity.other.attribute-name.id",
        "entity.other.attribute-name.id punctuation.definition.entity",
        "variable.parameter.url",
        "entity.name.section",
        "markup.changed",
        "meta.diff.header",
        "punctuation.definition.list",
        "source.tsx punctuation.section.embedded",
        "source.jsx punctuation.section.embedded",
        "keyword.operator",
        "storage.type.function.arrow",
        "keyword.operator.assignment",
        "punctuation.accessor.optional",
        "punctuation.definition.string.template",
        "punctuation.definition.template-expression",
        "keyword.operator.spread",
        "keyword.other.unit",
        "keyword",
        "entity.name.tag.css",
        "keyword.operator.new",
        "storage.modifier",
        "storage.type",
        "storage.type.function",
        "storage"
      ],
      "settings": {
        "foreground": "#F286C4",
        "fontStyle": ""
      }
    },
    {
      "scope": [],
      "settings": {
        "foreground": "#F286C4",
        "fontStyle": "italic"
      }
    },
    {
      "scope": [
        "link",
        "markup.underline.link",
        "constant.other.reference.link.markdown"
      ],
      "settings": {
        "foreground": "#F286C4",
        "fontStyle": "underline"
      }
    },
    {
      "scope": [
        "support.function",
        "string",
        "punctuation.definition.string",
        "constant.language.import-export-all",
        "meta.tag string",
        "markup.heading.setext",
        "meta.separator.markdown",
        "meta.property-value",
        "meta.property-value constant.other",
        "punctuation.section.embedded.begin.php",
        "punctuation.section.embedded.end.php",
        "markup.inserted",
        "string.template"
      ],
      "settings": {
        "foreground": "#E7EE98",
        "fontStyle": ""
      }
    },
    {
      "scope": [],
      "settings": {
        "foreground": "#E7EE98",
        "fontStyle": "italic"
      }
    },
    {
      "scope": [
        "meta.embedded",
        "source.groovy.embedded",
        "meta.template.expression",
        "punctuation.definition.variable",
        "support.variable.property.dom",
        "support.variable.dom",
        "support.variable.property",
        "string.interpolated.pug variable",
        "punctuation",
        "meta.brace.round.js"
      ],
      "settings": {
        "foreground": "#F6F6F4"
      }
    },
    {
      "scope": [
        "entity.other.attribute-name.class",
        "entity.other.attribute-name punctuation.definition.entity",
        "markup.deleted",
        "punctuation.definition.markdown",
        "storage.modifier.pointer",
        "punctuation.definition.typeparameters",
        "punctuation.definition.directive",
        "entity.other.inherited-class",
        "punctuation.definition.entity.css",
        "entity.other.attribute-name.id.css",
        "entity.name.tag"
      ],
      "settings": {
        "foreground": "#F6F6F4",
        "fontStyle": ""
      }
    },
    {
      "scope": [
        "constant.character.escape",
        "variable.language.special.self",
        "meta.tag.metadata.doctype string",
        "meta.tag.sgml.doctype",
        "markup.inline.raw",
        "meta.link punctuation.definition.string",
        "meta.image punctuation.definition.string",
        "meta.diff.range",
        "constant.other.color",
        "entity.name.tag.wildcard",
        "constant",
        "support.type.property-name.css",
        "entity.other.attribute-name.tsx"
      ],
      "settings": {
        "foreground": "#F6F6F4",
        "fontStyle": ""
      }
    },
    {
      "scope": ["variable.other.property"],
      "settings": {
        "foreground": "#F6F6F4",
        "fontStyle": ""
      }
    },
    {
      "scope": ["constant.numeric", "entity.name.tag.html"],
      "settings": {
        "foreground": "#BF9EEE",
        "fontStyle": ""
      }
    },
    {
      "scope": ["constant.language"],
      "settings": {
        "foreground": "#BF9EEE",
        "fontStyle": ""
      }
    },
    {
      "scope": [],
      "settings": {
        "foreground": "#F6F6F4",
        "fontStyle": "bold"
      }
    },
    {
      "scope": [
        "variable.argument",
        "meta.function.parameter variable",
        "punctuation.definition.binding-pattern.array",
        "source.rust meta.type_params.rust"
      ],
      "settings": {
        "foreground": "#c9c7c2",
        "fontStyle": ""
      }
    },
    {
      "scope": ["punctuation.definition.comment", "comment"],
      "settings": {
        "foreground": "#7B7F8B",
        "fontStyle": ""
      }
    },
    {
      "scope": ["punctuation.separator", "punctuation.accessor"],
      "settings": {
        "foreground": "#7B7F8B",
        "fontStyle": ""
      }
    },
    {
      "scope": [
        "punctuation.definition.entity.html",
        "constant.character.entity.named.emsp.html",
        "meta.property-list entity.name.tag.css",
        "meta.tag entity.other.attribute-name",
        "property"
      ],
      "settings": {
        "foreground": "#F6F6F4",
        "fontStyle": ""
      }
    },
    {
      "scope": [],
      "settings": {
        "foreground": "#F6F6F4",
        "fontStyle": ""
      }
    },
    {
      "scope": ["punctuation.definition.tag"],
      "settings": {
        "foreground": "#F6F6F4",
        "fontStyle": ""
      }
    },
    {
      "scope": ["entity.name.section.markdown"],
      "settings": {
        "foreground": "#c9c7c2",
        "fontStyle": "bold"
      }
    },
    {
      "scope": "markup.bold",
      "settings": {
        "fontStyle": "bold"
      }
    },
    {
      "scope": ["markup.italic"],
      "settings": {
        "fontStyle": "italic"
      }
    }
  ]
}
